{
"type": "FeatureCollection",
"name": "ldis",
"features": [
{ "type": "Feature", "properties": { "nombre": "Lugar 1", "clasificacion": "AS-PDI", "url": "https://www.google.es/" }, "geometry": { "type": "Point", "coordinates": [ -3.7038, 40.4168 ] } },
{ "type": "Feature", "properties": { "nombre": "Lugar 2", "clasificacion": "LU-PDI", "url": "https://www.google.es/" }, "geometry": { "type": "Point", "coordinates": [ -3.8196, 40.4372 ] } },
{ "type": "Feature", "properties": { "nombre": "Lugar 3", "clasificacion": "PP-PDI", "url": "https://www.google.es/" }, "geometry": { "type": "Point", "coordinates": [ -3.6885, 40.448 ] } },
{ "type": "Feature", "properties": { "nombre": "Hola", "clasificacion": "AS-PDI", "url": "https://www.google.com" }, "geometry": { "type": "Point", "coordinates": [ -3.786833786863271, 40.412409886058981 ] } }
]
}
