{
    "type": "FeatureCollection",
    "features": [
      {
        "type": "Feature",
        "properties": {
          "nombre": "Lugar 1",
          "url": "https://www.google.es/"
        },
        "geometry": {
          "type": "Point",
          "coordinates": [-3.7038, 40.4168]
        }
      },
      {
        "type": "Feature",
        "properties": {
          "nombre": "Lugar 2",
          "url": "https://www.google.es/"
        },
        "geometry": {
          "type": "Point",
          "coordinates": [-3.8196, 40.4372]
        }
      },
      {
        "type": "Feature",
        "properties": {
          "nombre": "Lugar 3",
          "url": "https://www.google.es/"
        },
        "geometry": {
          "type": "Point",
          "coordinates": [-3.6885, 40.4480]
        }
      }
    ]
  }
  