{
  "type": "FeatureCollection",
  "features": [
    {
      "type": "Feature",
      "properties": {
        "nombre": "Lugar 1",
        "clasificacion": "AS-PDI",
        "url": "https://www.google.es/"
      },
      "geometry": {
        "type": "Point",
        "coordinates": [-3.7038, 40.4168]
      }
    },
    {
      "type": "Feature",
      "properties": {
        "nombre": "Lugar 2",
        "clasificacion": "LU-PDI",
        "url": "https://www.google.es/"
      },
      "geometry": {
        "type": "Point",
        "coordinates": [-3.8196, 40.4372]
      }
    },
    {
      "type": "Feature",
      "properties": {
        "nombre": "Lugar 3",
        "clasificacion": "PP-PDI",
        "url": "https://www.google.es/"
      },
      "geometry": {
        "type": "Point",
        "coordinates": [-3.6885, 40.4480]
      }
    }
  ]
}
  